cobra2d/__init__.py
cobra2d/error.py
cobra2d/utils.py
cobra2d/constraints/__init__.py
cobra2d/constraints/constraints.py
cobra2d/constraints/linker.py
cobra2d/constraints/phase.py
cobra2d/constraints/transfer.py
cobra2d/constraints/transport.py
cobra2d/duplication/__init__.py
cobra2d/duplication/duplication.py
cobra2d/duplication/merging.py
cobra2d/duplication/normalization.py
cobra2d/duplication/reactions.py
cobra2d/optimization/__init__.py
cobra2d/optimization/parsimonious.py
cobra2d/resources/__init__.py
cobra2d/visualization/__init__.py
cobra2d/visualization/converter.py
cobra2d/visualization/helper.py
Cobra2D-0.5.0.dist-info/METADATA
Cobra2D-0.5.0.dist-info/WHEEL
Cobra2D-0.5.0.dist-info/top_level.txt
Cobra2D-0.5.0.dist-info/RECORD
