Metadata-Version: 2.1
Name: Cobra2D
Version: 0.5.0
Summary: A package for building time- and space-resolved metabolic models.
Home-page: https://github.com/Toepfer-Lab/Cobra2D
Author: "Jan-Niklas Weder, Stefano Camborda La Cruz, Nadine Töpfer
Author-email: ntoepfer@uni-koeln.de
Project-URL: Bug Tracker, https://github.com/Toepfer-Lab/Cobra2D/issues
Classifier: Programming Language :: Python :: 3
Classifier: Operating System :: OS Independent
Requires-Python: >=3.7
Requires-Dist: prettytable
Requires-Dist: rich
Requires-Dist: cobra (>=0.25.0)
Requires-Dist: typing-extensions
Requires-Dist: xmlschema
Requires-Dist: ipycytoscape
Requires-Dist: networkx
Requires-Dist: IPython
Requires-Dist: ipywidgets (>=7.6.0)
Requires-Dist: graphviz
Requires-Dist: igraph
Requires-Dist: requests
Requires-Dist: tqdm
Requires-Dist: importlib-resources
